rubikencryptor/__init__.py
rubikencryptor/rubikencryptor.py
rubikencryptor-1.0.10.dist-info/METADATA
rubikencryptor-1.0.10.dist-info/WHEEL
rubikencryptor-1.0.10.dist-info/top_level.txt
rubikencryptor-1.0.10.dist-info/RECORD
