Metadata-Version: 2.1
Name: rubikencryptor
Version: 1.0.10
Summary: Image Cryptography Based on Rubix's Cube Principle
Home-page: https://github.com/dannyi96/Image-Cryptography
Author: Daniel Isaac
Author-email: danielbcbs2@gmail.com
License: MIT
Classifier: Programming Language :: Python :: 3
Classifier: License :: OSI Approved :: MIT License
Classifier: Operating System :: OS Independent
Requires-Dist: numpy (>=1.20.2)
Requires-Dist: Pillow (>=8.4.0)
